stocks/__init__.py
stocks/info.py
tradingtools-0.0.1.dist-info/LICENCE
tradingtools-0.0.1.dist-info/METADATA
tradingtools-0.0.1.dist-info/WHEEL
tradingtools-0.0.1.dist-info/top_level.txt
tradingtools-0.0.1.dist-info/RECORD
