Metadata-Version: 2.1
Name: tradingtools
Version: 0.0.1
Summary: Tools for trading
Author: OverclockedD2
Author-email: <overclockedd2@gmail.com>
Keywords: python
Classifier: Development Status :: 1 - Planning
Classifier: Intended Audience :: Other Audience
Classifier: Programming Language :: Python :: 3
License-File: LICENCE
